odoo/addons/account_invoice_report_utm/README.rst
odoo/addons/account_invoice_report_utm/__init__.py
odoo/addons/account_invoice_report_utm/__manifest__.py
odoo/addons/account_invoice_report_utm/i18n/account_invoice_report_utm.pot
odoo/addons/account_invoice_report_utm/i18n/account_invoice_report_utm_campaign.pot
odoo/addons/account_invoice_report_utm/readme/CONTRIBUTORS.rst
odoo/addons/account_invoice_report_utm/readme/DESCRIPTION.rst
odoo/addons/account_invoice_report_utm/report/__init__.py
odoo/addons/account_invoice_report_utm/report/account_invoice_report.py
odoo/addons/account_invoice_report_utm/static/description/icon.png
odoo/addons/account_invoice_report_utm/static/description/index.html
odoo_addon_account_invoice_report_utm-15.0.1.0.0.2.dist-info/METADATA
odoo_addon_account_invoice_report_utm-15.0.1.0.0.2.dist-info/WHEEL
odoo_addon_account_invoice_report_utm-15.0.1.0.0.2.dist-info/top_level.txt
odoo_addon_account_invoice_report_utm-15.0.1.0.0.2.dist-info/RECORD
